{
	"configurations" : 
	[
		{
			"directories" : 
			[
				{
					"build" : ".",
					"jsonFile" : "directory-.-Debug-d0094a50bb2071803777.json",
					"minimumCMakeVersion" : 
					{
						"string" : "3.20"
					},
					"projectIndex" : 0,
					"source" : ".",
					"targetIndexes" : 
					[
						0,
						1
					]
				}
			],
			"name" : "Debug",
			"projects" : 
			[
				{
					"directoryIndexes" : 
					[
						0
					],
					"name" : "Spooflight",
					"targetIndexes" : 
					[
						0,
						1
					]
				}
			],
			"targets" : 
			[
				{
					"directoryIndex" : 0,
					"id" : "Spooflight::@6890427a1f51a3e7e1df",
					"jsonFile" : "target-Spooflight-Debug-6bc3d1d6ab354ec32b2c.json",
					"name" : "Spooflight",
					"projectIndex" : 0
				},
				{
					"directoryIndex" : 0,
					"id" : "SpooflightTest::@6890427a1f51a3e7e1df",
					"jsonFile" : "target-SpooflightTest-Debug-c62ad979d30997d7bc17.json",
					"name" : "SpooflightTest",
					"projectIndex" : 0
				}
			]
		}
	],
	"kind" : "codemodel",
	"paths" : 
	{
		"build" : "C:/Users/angel/Desktop/spooflight/build",
		"source" : "C:/Users/angel/Desktop/spooflight/Core"
	},
	"version" : 
	{
		"major" : 2,
		"minor" : 8
	}
}
